{
  "data": [
    {
      "name": "MD2",
      "fullname": "Matem치tica Discreta 2",
      "frequencies": ["3 de dezembro", "21 de janeiro"],
      "resource": ["칄 no recurso que se faz o curso!"]
    },
    {
      "name": "IO",
      "fullname": "Investiga칞칚o Operacional",
      "frequencies": ["16 dezembro [TP1] \n23 de novembro 맙 13:30h [TP2] 游둣","17 de janeiro 맙 15h [TP1]\n18 de janeiro 맙 13:30h [TP2]"]
    },
    {
      "name": "SIR",
      "fullname": "Sistemas de Informa칞칚o em Rede",
      "frequencies": ["22 de Novembro 맙 15h [TP1]"],
      "work": ["1췈 Trabalho pr치tico: \nEntrega: 16 de dezembro \nApresenta칞칚o: nas aulas a seguir \n","2췈 Trabalho pr치trico: \nEntrega: 13 de janeiro \nApresenta칞칚o: nas aulas a seguir"]
    },
    {
      "name": "IEOP",
      "fullname": "Integra칞칚o de Empresa",
      "work": ["Relat칩rio: \nEntrega: 16 de janeiro \nApresenta칞칚o: 17 de janeiro "]
    },
    {
      "name": "ALGA",
      "fullname": "Algebra Linear e Geometria Analitica 游땴游땴",
      "frequencies": ["9 de Novembro","10 de janeiro\n","Pr치tica: 14 de dezembro"]
    }
  ]    
}
