{
    "guild": {
        "id": "766278332500803604"
    },
    "timmers": {
        "meals": {
            "cronTime": "0 8 * * 0-5",
            "channelId": "772155762239471657"
        }
    },
    "reacts": [
        {
            "messageId": "779507900636463155",
            "emoji": "📖",
            "roleId": "795334538397089792"
        },
        {
            "messageId": "779508151874879540",
            "emoji": "📂",
            "roleId": "795334575164358676"
        },
        {
            "messageId": "779508285111140353",
            "emoji": "🥳",
            "roleId": "795334598124109834"
        },
        {
            "messageId": "779508430473396235",
            "emoji": "🎵",
            "roleId": "795334686443307049"
        },
        {
            "messageId": "779508742692536340",
            "emoji": "🍴",
            "roleId": "795334720731742308"
        },
        {
            "messageId": "795074401259094046",
            "emoji": "🔴",
            "roleId": "795072574467604510"
        },
        {
            "messageId": "795074401259094046",
            "emoji": "🔵",
            "roleId": "795072357744115743"
        },
        {
            "messageId": "795074401259094046",
            "emoji": "🟠",
            "roleId": "795072548629905408"
        },
        {
            "messageId": "795074401259094046",
            "emoji": "🟢",
            "roleId": "795072447304302624"
        },
        {
            "messageId": "795074401259094046",
            "emoji": "🟡",
            "roleId": "795072523371806761"
        },
        {
            "messageId": "795074401259094046",
            "emoji": "🟣",
            "roleId": "795072421627428864"
        }
    ]
}